.gitignore
.gitmodules
CHANGES.txt
LICENSE.txt
README.rst
bootstrap.py
buildout.cfg
setup.cfg
setup.py
css/__init__.py
css.css3githubbuttons.egg-info/PKG-INFO
css.css3githubbuttons.egg-info/SOURCES.txt
css.css3githubbuttons.egg-info/dependency_links.txt
css.css3githubbuttons.egg-info/entry_points.txt
css.css3githubbuttons.egg-info/namespace_packages.txt
css.css3githubbuttons.egg-info/not-zip-safe
css.css3githubbuttons.egg-info/requires.txt
css.css3githubbuttons.egg-info/top_level.txt
css/css3githubbuttons/__init__.py
css/css3githubbuttons/test_css3_github_buttons.txt
css/css3githubbuttons/resources/css3-github-buttons/.gitignore
css/css3githubbuttons/resources/css3-github-buttons/LICENSE.txt
css/css3githubbuttons/resources/css3-github-buttons/README.md
css/css3githubbuttons/resources/css3-github-buttons/gh-buttons.css
css/css3githubbuttons/resources/css3-github-buttons/gh-buttons.min.css
css/css3githubbuttons/resources/css3-github-buttons/gh-icons.png
css/css3githubbuttons/resources/css3-github-buttons/index.html
css/css3githubbuttons/resources/css3-github-buttons/ext_button_all/README.md
css/css3githubbuttons/resources/css3-github-buttons/ext_button_all/gh-buttons.css
css/css3githubbuttons/resources/css3-github-buttons/ext_button_all/gh-icons-all.png
css/css3githubbuttons/resources/css3-github-buttons/ext_button_all/gh-icons-black.png
css/css3githubbuttons/resources/css3-github-buttons/ext_button_all/gh-icons-blue.png
css/css3githubbuttons/resources/css3-github-buttons/ext_button_all/gh-icons-brown.png
css/css3githubbuttons/resources/css3-github-buttons/ext_button_all/gh-icons-dblue.png
css/css3githubbuttons/resources/css3-github-buttons/ext_button_all/gh-icons-green.png
css/css3githubbuttons/resources/css3-github-buttons/ext_button_all/gh-icons-lblue.png
css/css3githubbuttons/resources/css3-github-buttons/ext_button_all/gh-icons-lime.png
css/css3githubbuttons/resources/css3-github-buttons/ext_button_all/gh-icons-orange.png
css/css3githubbuttons/resources/css3-github-buttons/ext_button_all/gh-icons-pink.png
css/css3githubbuttons/resources/css3-github-buttons/ext_button_all/gh-icons-purple.png
css/css3githubbuttons/resources/css3-github-buttons/ext_button_all/gh-icons-red.png
css/css3githubbuttons/resources/css3-github-buttons/ext_button_all/gh-icons-white.png
