Metadata-Version: 1.0
Name: css.css3githubbuttons
Version: 2.1
Summary: Fanstatic packaging of CSS3 GitHub Buttons
Home-page: https://github.com/davidjb/css.css3githubbuttons
Author: Fanstatic Developers
Author-email: fanstatic@googlegroups.com
License: BSD
Keywords: fanstatic css3 buttons github
Platform: UNKNOWN
Classifier: Programming Language :: Python
Classifier: Topic :: Internet :: WWW/HTTP
